{"jobs":[{"id":"27928376","title":"Information Security Specialist 1 of 1","location":"New Freedom, PA","salary_min":85800,"salary_max":114400,"type":"Contract","skills":"(SKILLS TO BE ASSIGNED )","start_date":"2026-04-27T00:00:00","end_date":"2027-04-23T00:00:00","openings":1,"remote_pct":0,"posted_at":"2026-04-07T15:32:23"},{"id":"27946016","title":"Software Developer - Senior","location":"Albany, NY","salary_min":0,"salary_max":0,"type":"Contract","skills":"Null","start_date":"2026-04-10T00:00:00","end_date":"2026-04-23T00:00:00","openings":1,"remote_pct":0,"posted_at":"2026-04-10T11:56:51"},{"id":"28028692","title":"Software Architect","location":"NY","salary_min":0,"salary_max":0,"type":"Contract","skills":"Null","start_date":"2026-04-13T00:00:00","end_date":"2026-04-20T00:00:00","openings":1,"remote_pct":0,"posted_at":"2026-04-13T13:57:12"},{"id":"28033747","title":"Architect - Mastery","location":"Boston, MA","salary_min":261300,"salary_max":348400,"type":"Full-time","skills":"(SKILLS TO BE ASSIGNED )","start_date":"2026-05-04T00:00:00","end_date":"2027-04-30T00:00:00","openings":1,"remote_pct":0,"posted_at":"2026-04-14T12:02:37"},{"id":"28033746","title":"Business Analyst- Mid Level","location":"Raleigh, NC","salary_min":88530,"salary_max":118040,"type":"Full-time","skills":"(SKILLS TO BE ASSIGNED )","start_date":"2026-05-04T00:00:00","end_date":"2027-04-30T00:00:00","openings":1,"remote_pct":0,"posted_at":"2026-04-14T12:02:36"},{"id":"28033738","title":"Project Manager","location":"Albany, NY","salary_min":0,"salary_max":0,"type":"Contract","skills":"Null","start_date":"2026-04-14T00:00:00","end_date":"2026-04-28T00:00:00","openings":1,"remote_pct":0,"posted_at":"2026-04-14T12:01:38"},{"id":"28033755","title":"Programmer","location":"U.S.","salary_min":0,"salary_max":0,"type":"Contract","skills":"Null","start_date":"2026-04-14T00:00:00","end_date":"2026-04-28T00:00:00","openings":1,"remote_pct":0,"posted_at":"2026-04-14T12:03:45"},{"id":"28033168","title":"Programmer - Programmer Analyst - Data Conversion - MS - MSDOC","location":"Jackson, MS","salary_min":0,"salary_max":0,"type":"Full-time","skills":"(SKILLS TO BE ASSIGNED )","start_date":"2026-04-14T00:00:00","end_date":"","openings":1,"remote_pct":0,"posted_at":"2026-04-14T10:50:08"},{"id":"28033342","title":"Data Engineer","location":"Malvern, PA","salary_min":109200,"salary_max":145600,"type":"Contract","skills":"(SKILLS TO BE ASSIGNED )","start_date":"2026-04-28T00:00:00","end_date":"2026-10-30T00:00:00","openings":1,"remote_pct":0,"posted_at":"2026-04-14T11:12:39"},{"id":"28033341","title":"Senior Software Engineer . Net","location":"Hagerstown, MD","salary_min":109200,"salary_max":145600,"type":"Contract","skills":"(SKILLS TO BE ASSIGNED )","start_date":"2026-05-05T00:00:00","end_date":"2027-05-03T00:00:00","openings":1,"remote_pct":0,"posted_at":"2026-04-14T11:12:38"},{"id":"27929073","title":"Systems Developer","location":"Albany, NY","salary_min":109200,"salary_max":145600,"type":"Contract","skills":"Null","start_date":"2026-04-07T00:00:00","end_date":"2026-04-21T00:00:00","openings":1,"remote_pct":0,"posted_at":"2026-04-07T16:50:55"},{"id":"27929051","title":"Software Architect","location":"Albany, NY","salary_min":124800,"salary_max":166400,"type":"Contract","skills":"Null","start_date":"2026-04-07T00:00:00","end_date":"2026-04-21T00:00:00","openings":1,"remote_pct":0,"posted_at":"2026-04-07T16:47:35"},{"id":"28032266","title":"GDOT Jr. QA Analyst","location":"GA 30308, GA","salary_min":67080,"salary_max":89440,"type":"Contract","skills":"(SKILLS TO BE ASSIGNED )","start_date":"2026-05-11T00:00:00","end_date":"2027-06-30T00:00:00","openings":1,"remote_pct":0,"posted_at":"2026-04-14T08:33:49"},{"id":"27927482","title":"IN-IDOH Sr .Net Developer","location":"46204","salary_min":0,"salary_max":0,"type":"Contract","skills":"(SKILLS TO BE ASSIGNED )","start_date":"2026-05-04T00:00:00","end_date":"2026-11-30T00:00:00","openings":1,"remote_pct":0,"posted_at":"2026-04-07T14:02:53"},{"id":"27927918","title":"IN-IDOH Senior EDI Developer","location":"46204","salary_min":0,"salary_max":0,"type":"Contract","skills":"(SKILLS TO BE ASSIGNED )","start_date":"2026-05-04T00:00:00","end_date":"2026-08-15T00:00:00","openings":1,"remote_pct":0,"posted_at":"2026-04-07T14:33:04"},{"id":"27915339","title":"Software Develooper","location":"Albany, NY","salary_min":109200,"salary_max":145600,"type":"Contract","skills":"Null","start_date":"2026-04-03T00:00:00","end_date":"2026-04-10T00:00:00","openings":1,"remote_pct":0,"posted_at":"2026-04-03T15:12:13"},{"id":"27952336","title":"IT Specialist","location":"Albany, NY","salary_min":0,"salary_max":0,"type":"Contract","skills":"Null","start_date":"2026-04-13T00:00:00","end_date":"2026-04-17T00:00:00","openings":1,"remote_pct":0,"posted_at":"2026-04-13T10:16:38"},{"id":"27952372","title":"Software Analyst","location":"AK","salary_min":0,"salary_max":0,"type":"Contract","skills":"Null","start_date":"2026-04-13T00:00:00","end_date":"2026-04-20T00:00:00","openings":1,"remote_pct":0,"posted_at":"2026-04-13T10:21:19"},{"id":"27896887","title":"Software Developer - Expert","location":"Albany, NY","salary_min":0,"salary_max":0,"type":"Contract","skills":"Null","start_date":"2026-04-01T00:00:00","end_date":"","openings":1,"remote_pct":0,"posted_at":"2026-04-01T10:24:10"},{"id":"27925782","title":"GDOT IT Senior Support Specialist 3","location":"Atlanta, GA","salary_min":83850,"salary_max":111800,"type":"Contract","skills":"(SKILLS TO BE ASSIGNED )","start_date":"2026-05-11T00:00:00","end_date":"2027-06-30T00:00:00","openings":2,"remote_pct":0,"posted_at":"2026-04-07T11:32:51"},{"id":"27952007","title":"Software ARchitect","location":"Albany, NY","salary_min":0,"salary_max":0,"type":"Contract","skills":"Null","start_date":"2026-04-13T00:00:00","end_date":"2026-04-17T00:00:00","openings":1,"remote_pct":0,"posted_at":"2026-04-13T09:37:00"},{"id":"27951872","title":"Systems ARchitect","location":"Albany, NY","salary_min":0,"salary_max":0,"type":"Contract","skills":"Null","start_date":"2026-04-13T00:00:00","end_date":"2026-04-16T00:00:00","openings":1,"remote_pct":0,"posted_at":"2026-04-13T09:30:20"},{"id":"28029553","title":"Software Architec","location":"Albany, NY","salary_min":0,"salary_max":0,"type":"Contract","skills":"Null","start_date":"2026-04-13T00:00:00","end_date":"2026-04-27T00:00:00","openings":1,"remote_pct":0,"posted_at":"2026-04-13T15:08:12"},{"id":"27924772","title":"Active Directory Engineer – Directory Services Consolidation","location":"Newport Beach, CA","salary_min":101400,"salary_max":135200,"type":"Full-time","skills":"(SKILLS TO BE ASSIGNED )","start_date":"2026-04-27T00:00:00","end_date":"2027-03-31T00:00:00","openings":1,"remote_pct":0,"posted_at":"2026-04-07T09:22:28"},{"id":"27950780","title":"Integration Engineer","location":"Durham, NC","salary_min":140400,"salary_max":187200,"type":"Full-time","skills":"(SKILLS TO BE ASSIGNED )","start_date":"2026-04-27T00:00:00","end_date":"2026-08-08T00:00:00","openings":1,"remote_pct":0,"posted_at":"2026-04-13T06:02:40"},{"id":"27950770","title":"Systems Analyst 3","location":"Austin, TX","salary_min":184860,"salary_max":246480,"type":"Full-time","skills":"(SKILLS TO BE ASSIGNED )","start_date":"2026-05-18T00:00:00","end_date":"2026-08-31T00:00:00","openings":1,"remote_pct":0,"posted_at":"2026-04-13T06:02:35"},{"id":"27950775","title":"Tally Lead - RRCC - RHEL Admin","location":"Downey, CA","salary_min":163800,"salary_max":218400,"type":"Full-time","skills":"(SKILLS TO BE ASSIGNED )","start_date":"2026-05-26T00:00:00","end_date":"2027-05-03T00:00:00","openings":1,"remote_pct":0,"posted_at":"2026-04-13T06:02:37"},{"id":"27951882","title":"Software Architect","location":"Albany, NY","salary_min":0,"salary_max":0,"type":"Contract","skills":"Null","start_date":"2026-04-13T00:00:00","end_date":"2026-04-16T00:00:00","openings":1,"remote_pct":0,"posted_at":"2026-04-13T09:32:12"},{"id":"27948527","title":"Embedded Software Engineer 3 (TPL)","location":"Chillicothe, IL","salary_min":82680,"salary_max":110240,"type":"Contract","skills":"(SKILLS TO BE ASSIGNED )","start_date":"2026-05-11T00:00:00","end_date":"2027-05-10T00:00:00","openings":1,"remote_pct":0,"posted_at":"2026-04-10T16:32:29"},{"id":"27922003","title":"Tester","location":"U.S.","salary_min":0,"salary_max":0,"type":"Contract","skills":"Null","start_date":"2026-04-06T00:00:00","end_date":"2026-04-13T00:00:00","openings":1,"remote_pct":0,"posted_at":"2026-04-06T16:06:05"},{"id":"27921795","title":"Software Developer","location":"Albany, NY","salary_min":0,"salary_max":0,"type":"Contract","skills":"Null","start_date":"2026-04-06T00:00:00","end_date":"2026-04-10T00:00:00","openings":1,"remote_pct":0,"posted_at":"2026-04-06T15:48:41"},{"id":"27921805","title":"Project Manager","location":"U.S.","salary_min":0,"salary_max":0,"type":"Contract","skills":"Null","start_date":"2026-04-06T00:00:00","end_date":"2026-04-10T00:00:00","openings":1,"remote_pct":0,"posted_at":"2026-04-06T15:51:30"},{"id":"27920925","title":"Programmer Expert","location":"Albany, NY","salary_min":109200,"salary_max":145600,"type":"Contract","skills":"Null","start_date":"2026-04-06T00:00:00","end_date":"2026-04-20T00:00:00","openings":1,"remote_pct":0,"posted_at":"2026-04-06T14:01:40"},{"id":"27946981","title":"Systems Architect","location":"Albany, NY","salary_min":0,"salary_max":0,"type":"Contract","skills":"Null","start_date":"2026-04-10T00:00:00","end_date":"2026-04-16T00:00:00","openings":1,"remote_pct":0,"posted_at":"2026-04-10T13:33:33"},{"id":"27946037","title":"Systems Developer Expert","location":"Albany, NY","salary_min":0,"salary_max":0,"type":"Contract","skills":"Null","start_date":"2026-04-10T00:00:00","end_date":"2026-04-24T00:00:00","openings":1,"remote_pct":0,"posted_at":"2026-04-10T12:00:24"},{"id":"27946098","title":"Business Analyst","location":"Albany, NY","salary_min":0,"salary_max":0,"type":"Contract","skills":"Null","start_date":"2026-04-10T00:00:00","end_date":"2026-04-14T00:00:00","openings":1,"remote_pct":0,"posted_at":"2026-04-10T12:05:11"},{"id":"27946151","title":"Software Developer","location":"Albany, NY","salary_min":0,"salary_max":0,"type":"Contract","skills":"Null","start_date":"2026-04-10T00:00:00","end_date":"2026-04-14T00:00:00","openings":1,"remote_pct":0,"posted_at":"2026-04-10T12:11:03"},{"id":"27946202","title":"Software Architect","location":"Albany, NY","salary_min":0,"salary_max":0,"type":"Contract","skills":"Null","start_date":"2026-04-10T00:00:00","end_date":"2026-04-15T00:00:00","openings":1,"remote_pct":0,"posted_at":"2026-04-10T12:19:12"},{"id":"27946159","title":"IT Specialist","location":"Albany, NY","salary_min":0,"salary_max":0,"type":"Contract","skills":"Null","start_date":"2026-04-10T00:00:00","end_date":"2026-04-15T00:00:00","openings":1,"remote_pct":0,"posted_at":"2026-04-10T12:13:44"},{"id":"27919672","title":"Developer - Application Developer III - MS - DFA","location":"Jackson, MS","salary_min":0,"salary_max":0,"type":"Full-time","skills":"(SKILLS TO BE ASSIGNED )","start_date":"2026-05-01T00:00:00","end_date":"","openings":1,"remote_pct":0,"posted_at":"2026-04-06T11:59:21"},{"id":"27951883","title":"Sr Data Engineer","location":"Blue Bell, PA","salary_min":109200,"salary_max":145600,"type":"Contract","skills":"(SKILLS TO BE ASSIGNED )","start_date":"2026-05-18T00:00:00","end_date":"2026-11-18T00:00:00","openings":1,"remote_pct":0,"posted_at":"2026-04-13T09:32:28"},{"id":"27918278","title":"UX Designer (II)","location":"New York, NY","salary_min":165875,"salary_max":221166,"type":"Contract","skills":"(SKILLS TO BE ASSIGNED )","start_date":"2026-04-06T00:00:00","end_date":"2026-09-20T00:00:00","openings":1,"remote_pct":0,"posted_at":"2026-04-06T09:52:37"},{"id":"27944113","title":"IA-DOM-DOIT-INTS3 Mt. Pleasant Field Services Support","location":"Mount Pleasant, IA","salary_min":0,"salary_max":0,"type":"Contract","skills":"(SKILLS TO BE ASSIGNED )","start_date":"2026-05-04T00:00:00","end_date":"2026-06-30T00:00:00","openings":1,"remote_pct":0,"posted_at":"2026-04-10T06:02:51"},{"id":"27983126","title":"Portfolio Attribution - Full Stack Engineer 70/30 Back End","location":"Westlake, TX","salary_min":93600,"salary_max":124800,"type":"Full-time","skills":"(SKILLS TO BE ASSIGNED )","start_date":"2026-04-13T00:00:00","end_date":"2027-04-16T00:00:00","openings":1,"remote_pct":0,"posted_at":"2026-04-13T12:12:49"},{"id":"27917047","title":"Software Developer 2","location":"Austin, TX","salary_min":175110,"salary_max":233480,"type":"Full-time","skills":"(SKILLS TO BE ASSIGNED )","start_date":"2026-05-04T00:00:00","end_date":"2026-08-31T00:00:00","openings":1,"remote_pct":0,"posted_at":"2026-04-06T06:02:43"},{"id":"27917049","title":"Systems Analyst 3","location":"Austin, TX","salary_min":175110,"salary_max":233480,"type":"Full-time","skills":"(SKILLS TO BE ASSIGNED )","start_date":"2026-05-04T00:00:00","end_date":"2026-08-31T00:00:00","openings":1,"remote_pct":0,"posted_at":"2026-04-06T06:02:45"},{"id":"27917044","title":"Integration Engineer","location":"Durham, NC","salary_min":144300,"salary_max":192400,"type":"Full-time","skills":"(SKILLS TO BE ASSIGNED )","start_date":"2026-04-20T00:00:00","end_date":"2026-08-10T00:00:00","openings":1,"remote_pct":0,"posted_at":"2026-04-06T06:02:41"},{"id":"27917045","title":"Specialist- Junior","location":"Raleigh, NC","salary_min":84240,"salary_max":112320,"type":"Full-time","skills":"(SKILLS TO BE ASSIGNED )","start_date":"2026-04-20T00:00:00","end_date":"2026-10-19T00:00:00","openings":1,"remote_pct":0,"posted_at":"2026-04-06T06:02:42"},{"id":"27917048","title":"Systems Analyst 3","location":"Austin, TX","salary_min":175110,"salary_max":233480,"type":"Full-time","skills":"(SKILLS TO BE ASSIGNED )","start_date":"2026-05-04T00:00:00","end_date":"2026-08-31T00:00:00","openings":1,"remote_pct":0,"posted_at":"2026-04-06T06:02:44"},{"id":"27942251","title":"Full Stack Developer / Lead Developer","location":"Brooklyn, NY","salary_min":132600,"salary_max":176800,"type":"Contract","skills":"Null","start_date":"2026-07-01T00:00:00","end_date":"","openings":1,"remote_pct":0,"posted_at":"2026-04-09T16:18:07"},{"id":"28039334","title":"Project Manager - PMP Certified","location":"Albany, NY","salary_min":124800,"salary_max":166400,"type":"Contract","skills":"Null","start_date":"2026-05-07T00:00:00","end_date":"2027-08-25T00:00:00","openings":1,"remote_pct":0,"posted_at":"2026-04-15T11:09:57"},{"id":"27915356","title":"Software Developer","location":"Albany, NY","salary_min":0,"salary_max":0,"type":"Contract","skills":"Null","start_date":"2026-04-03T00:00:00","end_date":"2026-04-10T00:00:00","openings":1,"remote_pct":0,"posted_at":"2026-04-03T15:14:47"},{"id":"27915399","title":"Tester","location":"Albany, NY","salary_min":78000,"salary_max":104000,"type":"Contract","skills":"Null","start_date":"2026-04-03T00:00:00","end_date":"2027-05-28T00:00:00","openings":1,"remote_pct":0,"posted_at":"2026-04-03T15:22:30"},{"id":"27941584","title":"IN-IDOH Data Scientist","location":"U.S.","salary_min":0,"salary_max":0,"type":"Contract","skills":"(SKILLS TO BE ASSIGNED )","start_date":"2026-05-11T00:00:00","end_date":"2026-11-30T00:00:00","openings":1,"remote_pct":0,"posted_at":"2026-04-09T15:02:57"},{"id":"27915266","title":"Systems Analyst 3","location":"Austin, TX","salary_min":175110,"salary_max":233480,"type":"Full-time","skills":"(SKILLS TO BE ASSIGNED )","start_date":"2026-05-01T00:00:00","end_date":"2026-08-31T00:00:00","openings":1,"remote_pct":0,"posted_at":"2026-04-03T15:02:26"},{"id":"27915026","title":"Business Analyst Expert","location":"Albany, NY","salary_min":109200,"salary_max":145600,"type":"Contract","skills":"Null","start_date":"2026-04-03T00:00:00","end_date":"2026-04-08T00:00:00","openings":1,"remote_pct":0,"posted_at":"2026-04-03T14:20:41"},{"id":"27915269","title":"Business Analyst 3","location":"Austin, TX","salary_min":165360,"salary_max":220480,"type":"Full-time","skills":"(SKILLS TO BE ASSIGNED )","start_date":"2026-04-27T00:00:00","end_date":"2026-08-31T00:00:00","openings":1,"remote_pct":0,"posted_at":"2026-04-03T15:02:27"},{"id":"27921921","title":"Tester- Senior","location":"Albany, NY","salary_min":78000,"salary_max":104000,"type":"Contract","skills":"Null","start_date":"2026-04-06T00:00:00","end_date":"2026-04-13T00:00:00","openings":1,"remote_pct":0,"posted_at":"2026-04-06T16:03:23"},{"id":"27915267","title":"Software ARchitect expert","location":"U.S.","salary_min":0,"salary_max":0,"type":"Contract","skills":"Null","start_date":"2026-04-03T00:00:00","end_date":"2026-04-09T00:00:00","openings":1,"remote_pct":0,"posted_at":"2026-04-03T15:02:27"},{"id":"27915265","title":"Systems Analyst 3","location":"Austin, TX","salary_min":175110,"salary_max":233480,"type":"Full-time","skills":"(SKILLS TO BE ASSIGNED )","start_date":"2026-05-01T00:00:00","end_date":"2026-08-31T00:00:00","openings":1,"remote_pct":0,"posted_at":"2026-04-03T15:02:25"},{"id":"28038253","title":"Principal Full Stack Engineer","location":"Washington, DC","salary_min":132600,"salary_max":176800,"type":"Contract","skills":"(SKILLS TO BE ASSIGNED )","start_date":"2026-05-11T00:00:00","end_date":"2027-04-30T00:00:00","openings":1,"remote_pct":0,"posted_at":"2026-04-15T08:52:35"},{"id":"28037671","title":"IA-DOM-DOIT-INTS4 Cloud/Platform/Systems Specialist","location":"IA 50309, IA","salary_min":0,"salary_max":0,"type":"Contract","skills":"(SKILLS TO BE ASSIGNED )","start_date":"2026-05-18T00:00:00","end_date":"2026-06-30T00:00:00","openings":1,"remote_pct":0,"posted_at":"2026-04-15T06:02:55"},{"id":"27939268","title":"Senior Manager, CEG Compensation & Planning","location":"Waltham, MA","salary_min":201240,"salary_max":268320,"type":"Full-time","skills":"(SKILLS TO BE ASSIGNED )","start_date":"2026-04-27T00:00:00","end_date":"2026-12-31T00:00:00","openings":1,"remote_pct":0,"posted_at":"2026-04-09T12:02:29"},{"id":"27939270","title":"Business Analyst Expert","location":"Raleigh, NC","salary_min":101790,"salary_max":135720,"type":"Full-time","skills":"(SKILLS TO BE ASSIGNED )","start_date":"2026-05-01T00:00:00","end_date":"2027-04-30T00:00:00","openings":1,"remote_pct":0,"posted_at":"2026-04-09T12:02:28"},{"id":"27938075","title":"Software Analyst","location":"Albany, NY","salary_min":0,"salary_max":0,"type":"Contract","skills":"Null","start_date":"2026-04-09T00:00:00","end_date":"2026-04-22T00:00:00","openings":1,"remote_pct":0,"posted_at":"2026-04-09T10:46:03"},{"id":"27938216","title":"Enterprise Architect","location":"Los Angeles, CA","salary_min":134550,"salary_max":179400,"type":"Full-time","skills":"(SKILLS TO BE ASSIGNED )","start_date":"2026-05-01T00:00:00","end_date":"2026-10-30T00:00:00","openings":1,"remote_pct":0,"posted_at":"2026-04-09T11:02:31"},{"id":"27938214","title":"Senior Agile Scrum/Flow Master","location":"Durham, NC","salary_min":119730,"salary_max":159640,"type":"Full-time","skills":"(SKILLS TO BE ASSIGNED )","start_date":"2026-04-20T00:00:00","end_date":"2027-04-19T00:00:00","openings":1,"remote_pct":0,"posted_at":"2026-04-09T11:02:29"},{"id":"28028801","title":"Software Architect","location":"Albany, NY","salary_min":0,"salary_max":0,"type":"Contract","skills":"Null","start_date":"2026-04-13T00:00:00","end_date":"2026-04-24T00:00:00","openings":1,"remote_pct":0,"posted_at":"2026-04-13T14:03:50"},{"id":"27937832","title":"Dynamics 365 Developer","location":"Maple Grove, MN","salary_min":95160,"salary_max":126880,"type":"Contract","skills":"(SKILLS TO BE ASSIGNED )","start_date":"2026-05-04T00:00:00","end_date":"2027-04-30T00:00:00","openings":1,"remote_pct":0,"posted_at":"2026-04-09T10:22:22"},{"id":"27929039","title":"Software Architect Expert","location":"Albany, NY","salary_min":124800,"salary_max":166400,"type":"Contract","skills":"Null","start_date":"2026-04-07T00:00:00","end_date":"2027-04-14T00:00:00","openings":1,"remote_pct":0,"posted_at":"2026-04-07T16:45:41"},{"id":"27937020","title":"Senior Cyber Security Analyst – Governance (Disaster Recovery, Business Impact)","location":"Fridley, MN","salary_min":109200,"salary_max":145600,"type":"Contract","skills":"(SKILLS TO BE ASSIGNED )","start_date":"2026-04-13T00:00:00","end_date":"2027-04-12T00:00:00","openings":1,"remote_pct":0,"posted_at":"2026-04-09T08:32:25"},{"id":"27915201","title":"Database Architect","location":"U.S.","salary_min":0,"salary_max":0,"type":"Contract","skills":"Null","start_date":"2026-04-03T00:00:00","end_date":"2026-04-09T00:00:00","openings":1,"remote_pct":0,"posted_at":"2026-04-03T14:49:49"},{"id":"27910610","title":"Software Developer","location":"Albany, NY","salary_min":111883,"salary_max":149178,"type":"Contract","skills":"Null","start_date":"2026-04-02T00:00:00","end_date":"2026-04-07T00:00:00","openings":1,"remote_pct":0,"posted_at":"2026-04-02T17:37:09"},{"id":"27910285","title":"IN-DOC-Logansport Transition Specialist","location":"Logansport, IN","salary_min":0,"salary_max":0,"type":"Contract","skills":"(SKILLS TO BE ASSIGNED )","start_date":"2026-04-09T00:00:00","end_date":"2026-12-31T00:00:00","openings":1,"remote_pct":0,"posted_at":"2026-04-02T17:03:05"},{"id":"27921667","title":"Software Architect","location":"U.S.","salary_min":0,"salary_max":0,"type":"Contract","skills":"Null","start_date":"2026-04-06T00:00:00","end_date":"2026-04-09T00:00:00","openings":1,"remote_pct":0,"posted_at":"2026-04-06T15:39:26"},{"id":"28029091","title":"Software Developer","location":"Albany, NY","salary_min":93600,"salary_max":124800,"type":"Contract","skills":"Null","start_date":"2026-04-13T00:00:00","end_date":"2026-04-27T00:00:00","openings":1,"remote_pct":0,"posted_at":"2026-04-13T14:21:18"},{"id":"27907199","title":"Business Analyst- Senior","location":"Raleigh, NC","salary_min":93990,"salary_max":125320,"type":"Full-time","skills":"(SKILLS TO BE ASSIGNED )","start_date":"2026-04-14T00:00:00","end_date":"2027-03-31T00:00:00","openings":1,"remote_pct":0,"posted_at":"2026-04-02T11:02:35"},{"id":"27933491","title":"Project Manager III","location":"Fort Worth, TX","salary_min":176873,"salary_max":235830,"type":"Full-time","skills":"(SKILLS TO BE ASSIGNED )","start_date":"2026-04-27T00:00:00","end_date":"2027-04-19T00:00:00","openings":1,"remote_pct":0,"posted_at":"2026-04-08T13:02:23"},{"id":"27939271","title":"Clinical Documentation Principal Trainer (Epic)","location":"Raleigh, NC","salary_min":144300,"salary_max":192400,"type":"Full-time","skills":"(SKILLS TO BE ASSIGNED )","start_date":"2026-04-27T00:00:00","end_date":"2027-04-01T00:00:00","openings":1,"remote_pct":0,"posted_at":"2026-04-09T12:02:29"},{"id":"28035612","title":"Software Developer","location":"Albany, NY","salary_min":109200,"salary_max":145600,"type":"Contract","skills":"Null","start_date":"2026-04-14T00:00:00","end_date":"2027-04-21T00:00:00","openings":2,"remote_pct":0,"posted_at":"2026-04-14T15:51:06"},{"id":"28029201","title":"TEster","location":"Albany, NY","salary_min":0,"salary_max":0,"type":"Contract","skills":"Null","start_date":"2026-04-13T00:00:00","end_date":"2026-04-27T00:00:00","openings":1,"remote_pct":0,"posted_at":"2026-04-13T14:34:53"},{"id":"27932214","title":"Systems Analyst 3","location":"Austin, TX","salary_min":196170,"salary_max":261560,"type":"Full-time","skills":"(SKILLS TO BE ASSIGNED )","start_date":"2026-05-18T00:00:00","end_date":"2026-08-31T00:00:00","openings":1,"remote_pct":0,"posted_at":"2026-04-08T11:02:31"},{"id":"27864222","title":"Programmer Expert","location":"Albany, NY","salary_min":0,"salary_max":0,"type":"Contract","skills":"Null","start_date":"2026-03-27T00:00:00","end_date":"2026-03-30T00:00:00","openings":1,"remote_pct":0,"posted_at":"2026-03-27T17:02:26"},{"id":"27836057","title":"Software Architect Expert","location":"U.S.","salary_min":0,"salary_max":0,"type":"Contract","skills":"Null","start_date":"2026-03-24T00:00:00","end_date":"2026-03-24T00:00:00","openings":1,"remote_pct":0,"posted_at":"2026-03-24T10:38:41"},{"id":"27868835","title":"Programmer","location":"Albany, NY","salary_min":0,"salary_max":0,"type":"Contract","skills":"Null","start_date":"2026-03-30T00:00:00","end_date":"2026-03-30T00:00:00","openings":1,"remote_pct":0,"posted_at":"2026-03-30T11:52:44"},{"id":"27840213","title":"Software Analyst - Expert","location":"Albany","salary_min":124800,"salary_max":166400,"type":"Contract","skills":"Null","start_date":"2026-04-27T00:00:00","end_date":"2027-04-29T00:00:00","openings":1,"remote_pct":0,"posted_at":"2026-03-24T14:08:51"},{"id":"27864239","title":"Software Architect","location":"U.S.","salary_min":0,"salary_max":0,"type":"Contract","skills":"Null","start_date":"2026-03-27T00:00:00","end_date":"2026-03-30T00:00:00","openings":1,"remote_pct":0,"posted_at":"2026-03-27T17:05:00"},{"id":"27899483","title":"Business Analyst - Mastery","location":"Springfield, MA","salary_min":152490,"salary_max":203320,"type":"Full-time","skills":"(SKILLS TO BE ASSIGNED )","start_date":"2026-04-13T00:00:00","end_date":"2026-06-30T00:00:00","openings":1,"remote_pct":0,"posted_at":"2026-04-01T12:02:38"},{"id":"27898795","title":"Tester","location":"NY","salary_min":85800,"salary_max":114400,"type":"Contract","skills":"Null","start_date":"2026-04-01T00:00:00","end_date":"2026-04-14T00:00:00","openings":2,"remote_pct":0,"posted_at":"2026-04-01T11:20:36"},{"id":"27897196","title":"Web Designer","location":"Albany, NY","salary_min":0,"salary_max":0,"type":"Contract","skills":"Null","start_date":"2026-04-01T00:00:00","end_date":"2026-04-03T00:00:00","openings":1,"remote_pct":0,"posted_at":"2026-04-01T10:40:22"},{"id":"27899249","title":"Software Architect","location":"Albany, NY","salary_min":0,"salary_max":0,"type":"Contract","skills":"Null","start_date":"2026-04-01T00:00:00","end_date":"2026-04-06T00:00:00","openings":1,"remote_pct":0,"posted_at":"2026-04-01T11:35:13"},{"id":"27896838","title":"Software Architect - Expert","location":"Albany, NY","salary_min":0,"salary_max":0,"type":"Contract","skills":"Null","start_date":"2026-04-01T00:00:00","end_date":"","openings":1,"remote_pct":0,"posted_at":"2026-04-01T10:21:41"},{"id":"27860020","title":"Software Architect - Expert","location":"Albany, NY","salary_min":0,"salary_max":0,"type":"Contract","skills":"Null","start_date":"2026-03-27T00:00:00","end_date":"2026-03-27T00:00:00","openings":1,"remote_pct":0,"posted_at":"2026-03-27T07:40:13"},{"id":"27897052","title":"Software Architect Expert","location":"Albany, NY","salary_min":0,"salary_max":0,"type":"Contract","skills":"Null","start_date":"2026-04-01T00:00:00","end_date":"","openings":1,"remote_pct":0,"posted_at":"2026-04-01T10:31:32"},{"id":"27856442","title":"IT Specialist - Expert","location":"new york, NY","salary_min":109200,"salary_max":145600,"type":"Contract","skills":"Null","start_date":"2026-05-05T00:00:00","end_date":"2027-04-30T00:00:00","openings":1,"remote_pct":0,"posted_at":"2026-03-26T13:44:27"},{"id":"27891227","title":"Systems Developer Expert","location":"Albany, NY","salary_min":109200,"salary_max":145600,"type":"Contract","skills":"Null","start_date":"2026-03-31T00:00:00","end_date":"2026-03-31T00:00:00","openings":1,"remote_pct":0,"posted_at":"2026-03-31T11:39:25"},{"id":"27891267","title":"Software Architect Expert","location":"Albany, NY","salary_min":0,"salary_max":0,"type":"Contract","skills":"Null","start_date":"2026-03-31T00:00:00","end_date":"2026-04-02T00:00:00","openings":1,"remote_pct":0,"posted_at":"2026-03-31T11:42:47"},{"id":"27891712","title":"SOftware Architect","location":"albany, NY","salary_min":0,"salary_max":0,"type":"Contract","skills":"Null","start_date":"2026-04-01T00:00:00","end_date":"2026-04-01T00:00:00","openings":1,"remote_pct":0,"posted_at":"2026-03-31T12:17:18"},{"id":"27889426","title":"Database Architect - EXPERT","location":"Albany, NY","salary_min":124800,"salary_max":166400,"type":"Contract","skills":"Null","start_date":"2026-03-31T00:00:00","end_date":"2026-04-13T00:00:00","openings":1,"remote_pct":0,"posted_at":"2026-03-31T10:08:05"},{"id":"27762524","title":"IT Specialist midlevel","location":"U.S.","salary_min":0,"salary_max":0,"type":"Contract","skills":"Null","start_date":"2026-03-12T00:00:00","end_date":"2026-03-26T00:00:00","openings":1,"remote_pct":0,"posted_at":"2026-03-12T14:17:47"},{"id":"27885875","title":"Project Manager Expert","location":"NY","salary_min":0,"salary_max":0,"type":"Contract","skills":"Null","start_date":"2026-03-30T00:00:00","end_date":"2026-03-31T00:00:00","openings":1,"remote_pct":0,"posted_at":"2026-03-30T15:28:06"},{"id":"27841277","title":"Fullstack Architect","location":"Brooklyn, NY","salary_min":156000,"salary_max":208000,"type":"Contract","skills":"Null","start_date":"2026-03-24T00:00:00","end_date":"","openings":1,"remote_pct":0,"posted_at":"2026-03-24T15:10:21"},{"id":"27841448","title":"Programmer Expert","location":"Albany, NY","salary_min":109200,"salary_max":145600,"type":"Contract","skills":"Null","start_date":"2026-03-24T00:00:00","end_date":"2026-04-07T00:00:00","openings":1,"remote_pct":0,"posted_at":"2026-03-24T15:19:00"},{"id":"27907197","title":"ZPA Network Engineer","location":"Harrisburg, PA","salary_min":142740,"salary_max":190320,"type":"Full-time","skills":"(SKILLS TO BE ASSIGNED )","start_date":"2026-04-20T00:00:00","end_date":"2026-06-30T00:00:00","openings":1,"remote_pct":0,"posted_at":"2026-04-02T11:02:34"},{"id":"27838701","title":"Expert Software Architect","location":"Albany, NY","salary_min":112320,"salary_max":149760,"type":"Contract","skills":"Null","start_date":"2026-06-01T00:00:00","end_date":"2027-11-30T00:00:00","openings":1,"remote_pct":0,"posted_at":"2026-03-24T12:19:50"},{"id":"27435909","title":"SSIS SQL Engineer","location":"Blue Bell, PA","salary_min":71760,"salary_max":95680,"type":"Full-time","skills":"(SKILLS TO BE ASSIGNED )","start_date":"2026-03-02T00:00:00","end_date":"2026-11-30T00:00:00","openings":1,"remote_pct":0,"posted_at":"2026-02-11T16:32:46"},{"id":"27435952","title":"Embedded Software Engineer III","location":"Chillicothe, IL","salary_min":84240,"salary_max":112320,"type":"Contract","skills":"(SKILLS TO BE ASSIGNED )","start_date":"2026-03-02T00:00:00","end_date":"2027-03-01T00:00:00","openings":1,"remote_pct":0,"posted_at":"2026-02-11T16:33:48"},{"id":"27435914","title":"Technical Product Owner","location":"Blue Bell, PA","salary_min":118560,"salary_max":158080,"type":"Contract","skills":"(SKILLS TO BE ASSIGNED )","start_date":"2026-03-02T00:00:00","end_date":"2026-09-02T00:00:00","openings":1,"remote_pct":0,"posted_at":"2026-02-11T16:32:52"},{"id":"27436011","title":"Sr. Performance Marketing Manager (SEM & App Search)","location":"Pasadena, CA","salary_min":112866,"salary_max":150488,"type":"Contract","skills":"(SKILLS TO BE ASSIGNED )","start_date":"2026-02-26T00:00:00","end_date":"2026-06-26T00:00:00","openings":1,"remote_pct":0,"posted_at":"2026-02-11T16:34:51"},{"id":"27435976","title":"Systems Analyst","location":"Augusta, ME","salary_min":91510,"salary_max":122013,"type":"Contract","skills":"(SKILLS TO BE ASSIGNED )","start_date":"2026-02-02T00:00:00","end_date":"2026-06-30T00:00:00","openings":1,"remote_pct":0,"posted_at":"2026-02-11T16:34:16"},{"id":"27435902","title":"QA Engineer","location":"Blue Bell, PA","salary_min":63960,"salary_max":85280,"type":"Full-time","skills":"(SKILLS TO BE ASSIGNED )","start_date":"2026-03-16T00:00:00","end_date":"2026-10-01T00:00:00","openings":1,"remote_pct":0,"posted_at":"2026-02-11T16:32:37"},{"id":"27435903","title":"QA Engineer","location":"Blue Bell, PA","salary_min":63960,"salary_max":85280,"type":"Full-time","skills":"(SKILLS TO BE ASSIGNED )","start_date":"2026-03-16T00:00:00","end_date":"2026-10-01T00:00:00","openings":1,"remote_pct":0,"posted_at":"2026-02-11T16:32:39"},{"id":"27810224","title":"Software Architect - Expert","location":"Albany, NY","salary_min":0,"salary_max":0,"type":"Contract","skills":"Null","start_date":"2026-03-20T00:00:00","end_date":"2026-03-20T00:00:00","openings":1,"remote_pct":0,"posted_at":"2026-03-20T10:37:37"},{"id":"27756362","title":"Software Architect","location":"NY","salary_min":0,"salary_max":0,"type":"Contract","skills":"Null","start_date":"2026-03-11T00:00:00","end_date":"2026-03-25T00:00:00","openings":1,"remote_pct":0,"posted_at":"2026-03-11T16:54:34"},{"id":"27803555","title":".NET Systems Developer","location":"Albany, NY","salary_min":109200,"salary_max":145600,"type":"Contract","skills":"Null","start_date":"2026-03-19T00:00:00","end_date":"","openings":1,"remote_pct":0,"posted_at":"2026-03-19T10:35:49"},{"id":"27789912","title":"TESTER Expert","location":"Albany","salary_min":0,"salary_max":0,"type":"Contract","skills":"Null","start_date":"2026-03-17T00:00:00","end_date":"2027-02-10T00:00:00","openings":1,"remote_pct":0,"posted_at":"2026-03-17T11:20:03"},{"id":"27799788","title":"Software Architect - Expert","location":"Albany, NY","salary_min":124800,"salary_max":166400,"type":"Contract","skills":"Null","start_date":"2026-03-18T00:00:00","end_date":"2026-03-23T00:00:00","openings":1,"remote_pct":0,"posted_at":"2026-03-18T14:26:28"},{"id":"27769640","title":"Lead Business Analyst","location":"Austin, TX","salary_min":121680,"salary_max":162240,"type":"Contract","skills":"(SKILLS TO BE ASSIGNED )","start_date":"2026-03-30T00:00:00","end_date":"","openings":2,"remote_pct":0,"posted_at":"2026-03-13T14:58:23"},{"id":"27792777","title":"Systems Developer Expert","location":"U.S.","salary_min":0,"salary_max":0,"type":"Contract","skills":"Null","start_date":"2026-03-17T00:00:00","end_date":"2026-03-17T00:00:00","openings":1,"remote_pct":0,"posted_at":"2026-03-17T15:08:08"},{"id":"27762279","title":"Tester - Senior","location":"U.S.","salary_min":0,"salary_max":0,"type":"Contract","skills":"Null","start_date":"2026-03-12T00:00:00","end_date":"2026-03-26T00:00:00","openings":1,"remote_pct":0,"posted_at":"2026-03-12T13:56:36"},{"id":"27788519","title":"Business Analyst","location":"Albany, NY","salary_min":109200,"salary_max":145600,"type":"Contract","skills":"Null","start_date":"2026-04-08T00:00:00","end_date":"2027-03-25T00:00:00","openings":1,"remote_pct":0,"posted_at":"2026-03-17T09:22:05"},{"id":"27760225","title":"Software ARchitect - Expert","location":"U.S.","salary_min":0,"salary_max":0,"type":"Contract","skills":"Null","start_date":"2026-03-12T00:00:00","end_date":"","openings":1,"remote_pct":0,"posted_at":"2026-03-12T11:01:54"},{"id":"27738095","title":"System Analyst","location":"New York, NY","salary_min":98280,"salary_max":131040,"type":"Contract","skills":"Null","start_date":"2026-04-09T00:00:00","end_date":"2027-12-31T00:00:00","openings":1,"remote_pct":0,"posted_at":"2026-03-10T10:59:10"},{"id":"27785714","title":"Software Developer - Senior","location":"NY","salary_min":101400,"salary_max":135200,"type":"Contract","skills":"Null","start_date":"2026-04-06T00:00:00","end_date":"2027-03-31T00:00:00","openings":1,"remote_pct":0,"posted_at":"2026-03-16T17:07:25"},{"id":"27737296","title":"Systems Developer","location":"Albany, NY","salary_min":93600,"salary_max":124800,"type":"Contract","skills":"Null","start_date":"2026-03-10T00:00:00","end_date":"","openings":1,"remote_pct":0,"posted_at":"2026-03-10T09:23:00"},{"id":"27737336","title":"SD WAN Engineer","location":"Edison, NJ","salary_min":85800,"salary_max":114400,"type":"Full-time","skills":"Null","start_date":"2026-02-09T00:00:00","end_date":"","openings":1,"remote_pct":0,"posted_at":"2026-03-10T09:30:44"},{"id":"27784804","title":"Software Developer Expert - HBITS-07-14639","location":"NY","salary_min":0,"salary_max":0,"type":"Contract","skills":"Null","start_date":"2026-03-16T00:00:00","end_date":"2026-03-16T00:00:00","openings":1,"remote_pct":0,"posted_at":"2026-03-16T16:28:27"},{"id":"27784426","title":"Software Architect - Expert","location":"U.S.","salary_min":0,"salary_max":0,"type":"Contract","skills":"Null","start_date":"2026-03-16T00:00:00","end_date":"2026-03-17T00:00:00","openings":1,"remote_pct":0,"posted_at":"2026-03-16T16:03:56"},{"id":"27784386","title":"Systems Developer Expert","location":"U.S.","salary_min":0,"salary_max":0,"type":"Contract","skills":"Null","start_date":"2026-03-16T00:00:00","end_date":"2026-03-17T00:00:00","openings":1,"remote_pct":0,"posted_at":"2026-03-16T16:02:19"},{"id":"27737316","title":"TESTER","location":"Albany, NY","salary_min":74880,"salary_max":99840,"type":"Contract","skills":"Null","start_date":"2026-03-10T00:00:00","end_date":"","openings":1,"remote_pct":0,"posted_at":"2026-03-10T09:26:56"},{"id":"27755382","title":"TESTER","location":"Albany, NY","salary_min":74880,"salary_max":99840,"type":"Contract","skills":"Null","start_date":"2026-03-10T00:00:00","end_date":"","openings":1,"remote_pct":0,"posted_at":"2026-03-11T14:41:22"},{"id":"27444482","title":"Sr. Oracle DBA with OCI  and Golden Gate","location":"New York, NY","salary_min":117000,"salary_max":156000,"type":"Contract","skills":"Null","start_date":"2026-03-12T00:00:00","end_date":"","openings":1,"remote_pct":0,"posted_at":"2026-02-12T17:35:54"},{"id":"27695551","title":"PROJECT MANAGER ( ONSITE)","location":"mENANDS, NY","salary_min":101400,"salary_max":135200,"type":"Contract","skills":"Null","start_date":"2026-03-02T00:00:00","end_date":"","openings":1,"remote_pct":0,"posted_at":"2026-03-02T13:25:43"},{"id":"27436017","title":"Salesforce Solutions Architect","location":"Chicago, IL","salary_min":148200,"salary_max":197600,"type":"Full-time","skills":"(SKILLS TO BE ASSIGNED )","start_date":"2026-02-23T00:00:00","end_date":"2026-12-31T00:00:00","openings":1,"remote_pct":0,"posted_at":"2026-02-11T16:34:58"},{"id":"27709173","title":"DOE Business Analyst - S. Mugwe - Rate Increase","location":"GA 30334, GA","salary_min":87204,"salary_max":116272,"type":"Contract","skills":"(SKILLS TO BE ASSIGNED )","start_date":"2023-09-08T00:00:00","end_date":"2023-09-12T00:00:00","openings":1,"remote_pct":0,"posted_at":"2026-03-04T11:02:58"},{"id":"27435957","title":"Sr Full Stack Developer(70% API and 30% Angular)","location":"Smithfield, RI","salary_min":118560,"salary_max":158080,"type":"Contract","skills":"(SKILLS TO BE ASSIGNED )","start_date":"2026-02-05T00:00:00","end_date":"2027-06-29T00:00:00","openings":1,"remote_pct":0,"posted_at":"2026-02-11T16:33:56"},{"id":"27435892","title":"Software Solutions Architect - Rhapsody Developer & Admin","location":"Lansing, MI","salary_min":98686,"salary_max":131581,"type":"Contract","skills":"(SKILLS TO BE ASSIGNED )","start_date":"2026-01-06T00:00:00","end_date":"2026-09-30T00:00:00","openings":1,"remote_pct":0,"posted_at":"2026-02-11T16:32:24"},{"id":"27434361","title":"IOS Software Developer","location":"Albany, NY","salary_min":109200,"salary_max":145600,"type":"Contract","skills":"Null","start_date":"2026-02-11T00:00:00","end_date":"","openings":1,"remote_pct":0,"posted_at":"2026-02-11T14:16:35"},{"id":"27424261","title":"IN-ISP- Car wash attendant","location":"Indianapolis, IN","salary_min":29125,"salary_max":38834,"type":"Contract","skills":"(SKILLS TO BE ASSIGNED )","start_date":"2026-03-02T00:00:00","end_date":"2026-12-31T00:00:00","openings":1,"remote_pct":0,"posted_at":"2026-02-10T10:32:49"},{"id":"27418677","title":"TESTER","location":"Albany, NY","salary_min":85800,"salary_max":114400,"type":"Contract","skills":"Null","start_date":"2026-02-09T00:00:00","end_date":"","openings":1,"remote_pct":0,"posted_at":"2026-02-09T12:22:15"},{"id":"27435896","title":"ServiceNow IRM Developer","location":"Grand Rapids, MI","salary_min":101400,"salary_max":135200,"type":"Full-time","skills":"(SKILLS TO BE ASSIGNED )","start_date":"2026-01-05T00:00:00","end_date":"2027-01-30T00:00:00","openings":1,"remote_pct":0,"posted_at":"2026-02-11T16:32:31"},{"id":"27435899","title":"Project Manager 3","location":"Dimondale, MI","salary_min":112991,"salary_max":150654,"type":"Contract","skills":"(SKILLS TO BE ASSIGNED )","start_date":"2026-02-16T00:00:00","end_date":"2026-11-07T00:00:00","openings":1,"remote_pct":0,"posted_at":"2026-02-11T16:32:33"},{"id":"27435895","title":"Technical Architect","location":"Blue Bell, PA","salary_min":148200,"salary_max":197600,"type":"Contract","skills":"(SKILLS TO BE ASSIGNED )","start_date":"2026-01-26T00:00:00","end_date":"2026-08-03T00:00:00","openings":1,"remote_pct":0,"posted_at":"2026-02-11T16:32:29"},{"id":"27357214","title":"155414 Mainframe Cobol Programmer","location":"Phoenix, AZ","salary_min":0,"salary_max":0,"type":"Full-time","skills":"Null","start_date":"2026-01-29T00:00:00","end_date":"","openings":1,"remote_pct":0,"posted_at":"2026-01-29T09:45:26"},{"id":"27177979","title":"Java Software Developer","location":"Menands, NY","salary_min":101400,"salary_max":135200,"type":"Contract","skills":"Null","start_date":"2026-03-02T00:00:00","end_date":"2026-07-31T00:00:00","openings":1,"remote_pct":0,"posted_at":"2026-01-26T12:52:21"},{"id":"27158934","title":"154561 Azure Engineer","location":"Jackson, MI","salary_min":0,"salary_max":0,"type":"Full-time","skills":"Null","start_date":"2026-01-21T00:00:00","end_date":"","openings":1,"remote_pct":100,"posted_at":"2026-01-21T12:19:56"}],"count":146}